.coveragerc
.gitignore
.pre-commit-config.yaml
.readthedocs.yml
CHANGELOG.md
CODE_OF_CONDUCT.md
CONTRIBUTING.rst
LICENSE.txt
MANIFEST.in
Makefile
README.rst
codecov.yml
inlang.config.js
pytest.ini
setup.cfg
setup.py
tox.ini
.github/workflows/i18n.yml
.github/workflows/release.yml
.github/workflows/test.yml
djrestframework_simplejwt.egg-info/PKG-INFO
djrestframework_simplejwt.egg-info/SOURCES.txt
djrestframework_simplejwt.egg-info/dependency_links.txt
djrestframework_simplejwt.egg-info/not-zip-safe
djrestframework_simplejwt.egg-info/requires.txt
djrestframework_simplejwt.egg-info/top_level.txt
docs/Makefile
docs/blacklist_app.rst
docs/conf.py
docs/creating_tokens_manually.rst
docs/customizing_token_claims.rst
docs/development_and_contributing.rst
docs/drf_yasg_integration.rst
docs/getting_started.rst
docs/index.rst
docs/rest_framework_simplejwt.rst
docs/settings.rst
docs/stateless_user_authentication.rst
docs/token_types.rst
licenses/LICENSE-django-rest-framework-jwt
licenses/LICENSE-django-rest-framework.md
rest_framework_simplejwt/__init__.py
rest_framework_simplejwt/authentication.py
rest_framework_simplejwt/backends.py
rest_framework_simplejwt/exceptions.py
rest_framework_simplejwt/models.py
rest_framework_simplejwt/serializers.py
rest_framework_simplejwt/settings.py
rest_framework_simplejwt/state.py
rest_framework_simplejwt/tokens.py
rest_framework_simplejwt/utils.py
rest_framework_simplejwt/views.py
rest_framework_simplejwt/locale/ar/LC_MESSAGES/django.mo
rest_framework_simplejwt/locale/ar/LC_MESSAGES/django.po
rest_framework_simplejwt/locale/cs/LC_MESSAGES/django.mo
rest_framework_simplejwt/locale/cs/LC_MESSAGES/django.po
rest_framework_simplejwt/locale/de/LC_MESSAGES/django.mo
rest_framework_simplejwt/locale/de/LC_MESSAGES/django.po
rest_framework_simplejwt/locale/es/LC_MESSAGES/django.mo
rest_framework_simplejwt/locale/es/LC_MESSAGES/django.po
rest_framework_simplejwt/locale/es_AR/LC_MESSAGES/django.mo
rest_framework_simplejwt/locale/es_AR/LC_MESSAGES/django.po
rest_framework_simplejwt/locale/es_CL/LC_MESSAGES/django.mo
rest_framework_simplejwt/locale/es_CL/LC_MESSAGES/django.po
rest_framework_simplejwt/locale/fa/LC_MESSAGES/django.mo
rest_framework_simplejwt/locale/fa/LC_MESSAGES/django.po
