Metadata-Version: 2.1
Name: djrestframework-simplejwt
Version: 1.22.0
Summary: A minimal JSON Web Token authentication plugin for Django REST Framework
Home-page: https://github.com/mowarlee/djangorestframework-simplejwt
Author: Mewar Lee
Author-email: leemowar@gmail.com
License: MIT
Classifier: Development Status :: 5 - Production/Stable
Classifier: Environment :: Web Environment
Classifier: Framework :: Django
Classifier: Framework :: Django :: 3.2
Classifier: Framework :: Django :: 4.0
Classifier: Framework :: Django :: 4.1
Classifier: Framework :: Django :: 4.2
Classifier: Intended Audience :: Developers
Classifier: License :: OSI Approved :: MIT License
Classifier: Operating System :: OS Independent
Classifier: Programming Language :: Python
Classifier: Programming Language :: Python :: 3
Classifier: Programming Language :: Python :: 3.10
Classifier: Programming Language :: Python :: 3.11
Classifier: Topic :: Internet :: WWW/HTTP
Requires-Python: >=3.10
Provides-Extra: test
Provides-Extra: lint
Provides-Extra: doc
Provides-Extra: dev
Provides-Extra: python-jose
Provides-Extra: crypto
License-File: LICENSE.txt
